{
  "id": "b407450e-c5e0-4af7-9c2b-7dfd2f5f0b10",
  "prevId": "ff805050-21ee-483b-80d7-457b27e526fb",
  "version": "7",
  "dialect": "postgresql",
  "tables": {
    "public.files": {
      "name": "files",
      "schema": "",
      "columns": {
        "file_id": {
          "name": "file_id",
          "type": "uuid",
          "primaryKey": true,
          "notNull": true,
          "default": "gen_random_uuid()"
        },
        "user_id": {
          "name": "user_id",
          "type": "uuid",
          "primaryKey": false,
          "notNull": true
        },
        "file_name": {
          "name": "file_name",
          "type": "text",
          "primaryKey": false,
          "notNull": true
        },
        "file_type": {
          "name": "file_type",
          "type": "text",
          "primaryKey": false,
          "notNull": true
        },
        "upload_timestamp": {
          "name": "upload_timestamp",
          "type": "timestamp",
          "primaryKey": false,
          "notNull": true,
          "default": "now()"
        },
        "proofreading_status": {
          "name": "proofreading_status",
          "type": "text",
          "primaryKey": false,
          "notNull": true
        },
        "version_number": {
          "name": "version_number",
          "type": "integer",
          "primaryKey": false,
          "notNull": true,
          "default": 1
        },
        "file_url": {
          "name": "file_url",
          "type": "text",
          "primaryKey": false,
          "notNull": true
        },
        "original_text": {
          "name": "original_text",
          "type": "text",
          "primaryKey": false,
          "notNull": false
        },
        "current_text": {
          "name": "current_text",
          "type": "text",
          "primaryKey": false,
          "notNull": false
        }
      },
      "indexes": {},
      "foreignKeys": {},
      "compositePrimaryKeys": {},
      "uniqueConstraints": {},
      "policies": {},
      "checkConstraints": {},
      "isRLSEnabled": false
    },
    "public.proofreading_logs": {
      "name": "proofreading_logs",
      "schema": "",
      "columns": {
        "log_id": {
          "name": "log_id",
          "type": "uuid",
          "primaryKey": true,
          "notNull": true,
          "default": "gen_random_uuid()"
        },
        "file_id": {
          "name": "file_id",
          "type": "uuid",
          "primaryKey": false,
          "notNull": true
        },
        "corrections": {
          "name": "corrections",
          "type": "json",
          "primaryKey": false,
          "notNull": true
        },
        "timestamp": {
          "name": "timestamp",
          "type": "timestamp",
          "primaryKey": false,
          "notNull": true,
          "default": "now()"
        }
      },
      "indexes": {},
      "foreignKeys": {},
      "compositePrimaryKeys": {},
      "uniqueConstraints": {},
      "policies": {},
      "checkConstraints": {},
      "isRLSEnabled": false
    }
  },
  "enums": {},
  "schemas": {},
  "sequences": {},
  "roles": {},
  "policies": {},
  "views": {},
  "_meta": {
    "columns": {},
    "schemas": {},
    "tables": {}
  }
}